sifeng/__init__.py
sifeng/__version__.py
sifeng/utils.py
sifeng/bnn/__init__.py
sifeng/bnn/loss.py
sifeng/bnn/modules/__init__.py
sifeng/bnn/modules/continer.py
sifeng/bnn/modules/linear.py
sifeng/bnn/modules/module.py
sifeng/dl/__init__.py
sifeng/dl/functional.py
sifeng/dl/loss.py
sifeng/dl/utils.py
sifeng/dl/models/__init__.py
sifeng/dl/models/ctts.py
sifeng/dl/modules/__init__.py
sifeng/dl/modules/positional_encoding.py
sifeng/dl/modules/sparse_model.py
sifeng/dl/modules/transformers.py
sifeng-0.5.1.dist-info/LICENSE
sifeng-0.5.1.dist-info/METADATA
sifeng-0.5.1.dist-info/WHEEL
sifeng-0.5.1.dist-info/top_level.txt
sifeng-0.5.1.dist-info/RECORD
