Metadata-Version: 2.1
Name: sifeng
Version: 0.5.1
Summary: The machine learning quant research framework.
Home-page: https://github.com/zty200489/sifeng
Author: Tianyuan Zhou
Author-email: zty200489@gmail.com
License: GPL
Classifier: Development Status :: 1 - Planning
Classifier: License :: OSI Approved :: GNU General Public License (GPL)
Classifier: Programming Language :: Python :: 3.8
Classifier: Topic :: Scientific/Engineering :: Mathematics
Requires-Python: >=3.8.0
License-File: LICENSE
Requires-Dist: tqdm
Requires-Dist: numpy
Requires-Dist: pandas
Requires-Dist: duckdb
Requires-Dist: joblib
Requires-Dist: requests
Requires-Dist: colorama
